crp/__init__.py
crp/__main__.py
crp/main.py
crp/py.typed
crp/types.py
crp/cmd/__init__.py
crp/cmd/suggest.py
crp-0.0.5.dist-info/METADATA
crp-0.0.5.dist-info/WHEEL
crp-0.0.5.dist-info/entry_points.txt
crp-0.0.5.dist-info/licenses/LICENSE
crp-0.0.5.dist-info/RECORD
