Metadata-Version: 2.4
Name: crp
Version: 0.0.5
Summary: Tools for cropping images.
Project-URL: Documentation, https://crp.bws.bio
Project-URL: Homepage, https://github.com/br3ndonland/crp
Project-URL: Repository, https://github.com/br3ndonland/crp
Author-email: Brendon Smith <bws@bws.bio>
License-Expression: MIT
License-File: LICENSE
Classifier: Natural Language :: English
Classifier: Programming Language :: Python :: 3
Classifier: Programming Language :: Python :: 3.12
Classifier: Programming Language :: Python :: 3.13
Classifier: Typing :: Typed
Requires-Python: <4,>=3.12
Requires-Dist: click<8.4,>=8.3
